DIL/Error.py
DIL/__init__.py
DIL/etc.py
DIL/generalization.py
DIL/rounding.py
DIL/suppression.py
DIL/crypto/AES256.py
DIL/crypto/FPE.py
DIL/crypto/OPE.py
DIL/crypto/__init__.py
DIL/crypto/hash/__init__.py
DIL/crypto/hash/sha256.py
DIL/randomization/__init__.py
DIL/randomization/noiseAdd.py
DIL/randomization/permutation.py
DIL/statistics/__init__.py
DIL/statistics/aggregation.py
DIL/statistics/microAggregation.py
DIL/util/__init__.py
DIL/util/datasetting.py
DIL-0.0.2.dist-info/LICENSE
DIL-0.0.2.dist-info/METADATA
DIL-0.0.2.dist-info/WHEEL
DIL-0.0.2.dist-info/top_level.txt
DIL-0.0.2.dist-info/RECORD
