Metadata-Version: 2.1
Name: DIL
Version: 0.0.2
Summary: 가명처리 기술을 손 쉽게 사용할 수 있는 라이브러리
Home-page: https://github.com/LRTK-CODER/DIL-Project
Author: DIL-Project
Author-email: lrtk@kakao.com
License: UNKNOWN
Platform: UNKNOWN
Classifier: Programming Language :: Python :: 3
Classifier: License :: OSI Approved :: MIT License
Classifier: Operating System :: OS Independent
Requires-Python: >=3.9
License-File: LICENSE
